gitsint/__init__.py
gitsint/instruments.py
gitsint/modules/__init__.py
gitsint/modules/profile/__init__.py
gitsint/modules/profile/friends.py
gitsint/modules/profile/profile.py
gitsint/modules/repos/__init__.py
gitsint/modules/repos/repository.py
gitsint/utils/gitleaks.py
gitsint-0.3.10.dist-info/LICENSE
gitsint-0.3.10.dist-info/LICENSE.md
gitsint-0.3.10.dist-info/METADATA
gitsint-0.3.10.dist-info/WHEEL
gitsint-0.3.10.dist-info/entry_points.txt
gitsint-0.3.10.dist-info/RECORD
